{
  "title": "Boere win \"Slag van Spandaukop\"",
  "description": "GRAAFF-REINET NEWS -&nbsp;The &lsquo;Slag...",
  "bodyText": "[{\"type\":\"paragraph\",\"text\":\"GRAAFF-REINET NEWS - The ‘Slag van Spandaukop’ between the Afrikaans and English golfers at the Graaff-Reinet Golf Club on Saturday, 8 March, was won by the Boere, 10 matches to six.\",\"html\":\"GRAAFF-REINET NEWS - The ‘Slag van Spandaukop’ between the Afrikaans and English golfers at the Graaff-Reinet Golf Club on Saturday, 8 March, was won by the Boere, 10 matches to six.\"},{\"type\":\"blockquote\",\"text\":\"The golf course was in great condition, and the balmy weather and rain-free skies resulted in a successful day.\"},{\"type\":\"paragraph\",\"text\":\"Great food, superb ambiance and good attendance on the deck kept the players celebrating.\",\"html\":\"Great food, superb ambiance and good attendance on the deck kept the players celebrating.\"},{\"type\":\"paragraph\",\"text\":\"Thanks to Noorsveld Chickens and Pick n Pay Graaff-Reinet, the players received lots of delightful prizes.\",\"html\":\"Thanks to Noorsveld Chickens and Pick n Pay Graaff-Reinet, the players received lots of delightful prizes.\"},{\"type\":\"paragraph\",\"text\":\"Wayne Myburgh, who had the longest drive among the men on Saturday, and club captain Derek Helm.\",\"html\":\"<span class=\\\"fr-img-caption fr-fic fr-dib class1\\\" style=\\\"width: 562px;\\\"><span class=\\\"fr-img-wrap\\\"><img src=\\\"https://cms.groupeditors.com//media/1/1///2ee28ca5-d388-4725-8a0b-8b5507d5705b.jpg\\\"><span class=\\\"fr-inner\\\">Wayne Myburgh, who had the longest drive among the men on Saturday, and club captain Derek Helm.</span></span></span>\"},{\"type\":\"paragraph\",\"text\":\"‘We bring you the latest Garden Route, Hessequa, Karoo news’\",\"html\":\"<strong fr-original-style=\\\"\\\" style=\\\"font-weight: bold; box-sizing: border-box;\\\"><em fr-original-style=\\\"\\\" style=\\\"box-sizing: border-box;\\\">‘We bring you the latest Garden Route, Hessequa, Karoo news’</em></strong>\"}]",
  "images": [
    {
      "url": "https://cms.groupeditors.com/img/b487b047-da46-4e1c-b3ba-545f5d3afa01.jpg?w=400&scale=both&quality=100",
      "alt": "Boere win \"Slag van Spandaukop\""
    },
    {
      "url": "https://cms.groupeditors.com//media/1/1///2ee28ca5-d388-4725-8a0b-8b5507d5705b.jpg",
      "alt": "Boere win \"Slag van Spandaukop\""
    },
    {
      "url": "https://cms.groupeditors.com/img//da8583d1-63d1-4456-aa28-f7a481d71f0c.png?w=300&h=200&mode=crop&scale=both&quality=80",
      "alt": "Press Reader Image"
    }
  ],
  "author": "",
  "tags": [],
  "videoUrls": [],
  "galleryLink": "",
  "ogImage": "https://cms.groupeditors.com/img/b487b047-da46-4e1c-b3ba-545f5d3afa01.jpg?crop=0,93,270,245"
}
