{
  "title": "DA vote raises eyebrows",
  "description": "KNYSNA NEWS - Knysna Independent Movement...",
  "bodyText": "[{\"type\":\"blockquote\",\"text\":\"When it came to voting on the referral of the complaint, three DA councillors broke ranks and voted against it.\"},{\"type\":\"paragraph\",\"text\":\"Alleged financial misconduct\",\"html\":\"Alleged financial misconduct\"},{\"type\":\"paragraph\",\"text\":\"Susan Campbell\",\"html\":\"<span class=\\\"fr-img-caption class1\\\" style=\\\"display: block; vertical-align: top; margin: 5px auto; text-align: center; width: 466px;\\\"><span class=\\\"fr-img-wrap\\\"><img src=\\\"https://cms.groupeditors.com//media/1/1/undefined/undefined/adcb0bab-08a2-4359-bdb6-4bf861d35d83.jpg\\\"><span class=\\\"fr-inner\\\">Susan Campbell</span></span>\\n</span>\"},{\"type\":\"paragraph\",\"text\":\"Code of Conduct\",\"html\":\"Code of Conduct\"},{\"type\":\"blockquote\",\"text\":\"Councillor Morton Gericke of the PBI left the meeting and logged on virtually, but was too late and missed the vote.\"},{\"type\":\"paragraph\",\"text\":\"‘We bring you the latest Garden Route, Hessequa, Karoo news’\",\"html\":\"<strong fr-original-style=\\\"\\\" style=\\\"font-weight: bold; box-sizing: border-box;\\\"><em fr-original-style=\\\"\\\" style=\\\"box-sizing: border-box;\\\">‘We bring you the latest Garden Route, Hessequa, Karoo news’</em></strong>\"},{\"type\":\"paragraph\",\"text\":\"For more Knysna-Plett Herald news, follow us on\\n                    Facebook,\\n                    X and\\n                    Instagram.\",\"html\":\"For more <b><i>Knysna-Plett Herald</i></b> news, follow us on\\n                    <b class=\\\"text-danger\\\"><a href=\\\"https://www.facebook.com/KnysnaPlettHerald/\\\" target=\\\"_blank\\\" style=\\\"text-decoration: none; cursor: pointer\\\">Facebook</a></b>,\\n                    <b class=\\\"text-danger\\\"><a href=\\\"https://twitter.com/KnysnaPlett\\\" target=\\\"_blank\\\" style=\\\"text-decoration: none; cursor: pointer\\\">X</a></b> and\\n                    <b class=\\\"text-danger\\\"><a href=\\\"https://www.instagram.com/knysnaplettherald/\\\" target=\\\"_blank\\\" style=\\\"text-decoration: none; cursor: pointer\\\">Instagram</a></b>.\"},{\"type\":\"paragraph\",\"text\":\"You can also check out our videos on our\\n                    YouTube channel or follow us on\\n                    TikTok.\",\"html\":\"You can also check out our videos on our\\n                    <b class=\\\"text-danger\\\"><a href=\\\"https://www.youtube.com/channel/UCrTKSG0b9GJSoT7kLPa7qCw/videos?view_as=subscriber \\\" target=\\\"_blank\\\" style=\\\"text-decoration: none; cursor: pointer\\\">YouTube</a></b> channel or follow us on\\n                    <b class=\\\"text-danger\\\"><a href=\\\"https://www.tiktok.com/@knysnaplettherald\\\" target=\\\"_blank\\\" style=\\\"text-decoration: none; cursor: pointer\\\">TikTok</a></b>.\"},{\"type\":\"paragraph\",\"text\":\"Subscribe to our\\n                    WhatsApp\\n                    channel and get news delivered straight to your phone.\",\"html\":\"Subscribe to our\\n                    <b class=\\\"text-danger\\\"><a href=\\\"https://whatsapp.com/channel/0029VaNwpHsFcovzVDNsRk2X\\\" target=\\\"_blank\\\" style=\\\"text-decoration: none; cursor: pointer\\\">WhatsApp</a></b>\\n                    channel and get news delivered straight to your phone.\"}]",
  "images": [
    {
      "url": "https://cms.groupeditors.com/img/09f2ea51-6ee4-446a-a0f2-06d79ca35846.jpg?w=400&scale=both&quality=100",
      "alt": "DA vote raises eyebrows"
    },
    {
      "url": "https://cms.groupeditors.com//media/1/1/undefined/undefined/adcb0bab-08a2-4359-bdb6-4bf861d35d83.jpg",
      "alt": "DA vote raises eyebrows"
    },
    {
      "url": "https://cms.groupeditors.com/img//b37ebbfd-27eb-4984-b2a7-62108b0f4470.jpg?w=245&mode=crop&scale=both&quality=100",
      "alt": "Knysna-Plett Herald 5 February 2026"
    }
  ],
  "author": "",
  "tags": [],
  "videoUrls": [],
  "galleryLink": "",
  "ogImage": "https://cms.groupeditors.com/img/09f2ea51-6ee4-446a-a0f2-06d79ca35846.jpg?crop=0,0,509,286"
}
