{
  "title": "Nekkies fire: Damage still unknown",
  "description": "KNYSNA NEWS - Multiple homes have reportedly...",
  "bodyText": "[{\"type\":\"paragraph\",\"text\":\"KNYSNA NEWS - Multiple homes have reportedly burned down in the Nekkies area this afternoon. The exact number of affected families remains unknown. Emergency services are on the scene. More details to follow as the situation develops.\",\"html\":\"KNYSNA NEWS - Multiple homes have reportedly burned down in the Nekkies area this afternoon. The exact number of affected families remains unknown. Emergency services are on the scene. More details to follow as the situation develops.\"},{\"type\":\"paragraph\",\"text\":\"‘We bring you the latest Garden Route, Hessequa, Karoo news’\",\"html\":\"<strong fr-original-style=\\\"\\\" style=\\\"font-weight: bold; box-sizing: border-box;\\\"><em fr-original-style=\\\"\\\" style=\\\"box-sizing: border-box;\\\">‘We bring you the latest Garden Route, Hessequa, Karoo news’</em></strong>\"}]",
  "images": [
    {
      "url": "https://cms.groupeditors.com/img/3e31428d-ec71-47f0-8100-fd2f4e5e993a.jpg?w=400&scale=both&quality=100",
      "alt": "Nekkies fire: Damage still unknown"
    },
    {
      "url": "https://cms.groupeditors.com/img//b37ebbfd-27eb-4984-b2a7-62108b0f4470.jpg?w=245&mode=crop&scale=both&quality=100",
      "alt": "Knysna-Plett Herald 5 February 2026"
    }
  ],
  "author": "",
  "tags": [],
  "videoUrls": [],
  "galleryLink": "",
  "ogImage": "https://cms.groupeditors.com/img/3e31428d-ec71-47f0-8100-fd2f4e5e993a.jpg?crop=0,113,525,408"
}
